widetrax/DataPreprocessing.py
widetrax/Grads.py
widetrax/Spectra.py
widetrax/__init__.py
widetrax/version.py
widetrax-1.1.1.dist-info/licenses/LICENSE
widetrax-1.1.1.dist-info/METADATA
widetrax-1.1.1.dist-info/WHEEL
widetrax-1.1.1.dist-info/top_level.txt
widetrax-1.1.1.dist-info/RECORD
