Metadata-Version: 2.4
Name: widetrax
Version: 1.1.1
Summary: Computes the Power Spectrum density (PSD) from SWOT data
Author-email: Amine Ouhechou <amine.ouhechou@univ-grenoble-alpes.fr>, Julien Le Sommer <julien.lesommer@univ-grenoble-alpes.fr>
License: Apache-2.0
Keywords: PSD,SWOT,Vorticity,Strain
Classifier: Programming Language :: Python :: 3
Classifier: License :: OSI Approved :: Apache Software License
Classifier: Operating System :: OS Independent
Requires-Python: >=3.9
License-File: LICENSE
Requires-Dist: cartopy
Requires-Dist: matplotlib
Requires-Dist: netCDF4
Requires-Dist: numpy
Requires-Dist: scipy
Requires-Dist: xarray
Requires-Dist: datetime
Requires-Dist: jax
Requires-Dist: jaxparrow
Requires-Dist: s3fs
Requires-Dist: natsort
Requires-Dist: pandas
Requires-Dist: opencv-python
Requires-Dist: opencv-contrib-python
Dynamic: license-file
